README.md
setup.py
MathMonkey.egg-info/PKG-INFO
MathMonkey.egg-info/SOURCES.txt
MathMonkey.egg-info/dependency_links.txt
MathMonkey.egg-info/top_level.txt
l0/column_addition.py