Metadata-Version: 1.0
Name: MathMonkey
Version: 0.1
Summary: A repetitive maths practice system.
Home-page: https://github.com/ikucan/MathMonkey
Author: Iztok Kucan
Author-email: iztok.kucan@gmail.com
License: UNKNOWN
Platform: UNKNOWN
